[{"name":"Colcha Alvor","title":"01alvor.jpg","year":"2018","season":"Primavera Verão","filename":"01alvor.jpg","src":"images/2018pv/quilts/01alvor.jpg","thumb":"images/2018pv/quilts/thumbs/01alvor.jpg","w":1597,"h":1351,"index":1},{"name":"01alvorazul.jpg","title":"01alvorazul.jpg","year":"2018","season":"Primavera Verão","filename":"01alvorazul.jpg","src":"images/2018pv/quilts/01alvorazul.jpg","thumb":"images/2018pv/quilts/thumbs/01alvorazul.jpg","w":1597,"h":1351,"index":2},{"name":"01alvorbranco.jpg","title":"01alvorbranco.jpg","year":"2018","season":"Primavera Verão","filename":"01alvorbranco.jpg","src":"images/2018pv/quilts/01alvorbranco.jpg","thumb":"images/2018pv/quilts/thumbs/01alvorbranco.jpg","w":1597,"h":1351,"index":3},{"name":"01alvorcreme.jpg","title":"01alvorcreme.jpg","year":"2018","season":"Primavera Verão","filename":"01alvorcreme.jpg","src":"images/2018pv/quilts/01alvorcreme.jpg","thumb":"images/2018pv/quilts/thumbs/01alvorcreme.jpg","w":1597,"h":1351,"index":4},{"name":"01alvorrosa.jpg","title":"01alvorrosa.jpg","year":"2018","season":"Primavera Verão","filename":"01alvorrosa.jpg","src":"images/2018pv/quilts/01alvorrosa.jpg","thumb":"images/2018pv/quilts/thumbs/01alvorrosa.jpg","w":1597,"h":1351,"index":5},{"name":"02moledobranco.jpg","title":"02moledobranco.jpg","year":"2018","season":"Primavera Verão","filename":"02moledobranco.jpg","src":"images/2018pv/quilts/02moledobranco.jpg","thumb":"images/2018pv/quilts/thumbs/02moledobranco.jpg","w":1766,"h":1417,"index":6},{"name":"02moledocinza.jpg","title":"02moledocinza.jpg","year":"2018","season":"Primavera Verão","filename":"02moledocinza.jpg","src":"images/2018pv/quilts/02moledocinza.jpg","thumb":"images/2018pv/quilts/thumbs/02moledocinza.jpg","w":1766,"h":1417,"index":7},{"name":"02moledorosa.jpg","title":"02moledorosa.jpg","year":"2018","season":"Primavera Verão","filename":"02moledorosa.jpg","src":"images/2018pv/quilts/02moledorosa.jpg","thumb":"images/2018pv/quilts/thumbs/02moledorosa.jpg","w":1766,"h":1417,"index":8},{"name":"02moledotaupe.jpg","title":"02moledotaupe.jpg","year":"2018","season":"Primavera Verão","filename":"02moledotaupe.jpg","src":"images/2018pv/quilts/02moledotaupe.jpg","thumb":"images/2018pv/quilts/thumbs/02moledotaupe.jpg","w":1766,"h":1417,"index":9},{"name":"03miroazul.jpg","title":"03miroazul.jpg","year":"2018","season":"Primavera Verão","filename":"03miroazul.jpg","src":"images/2018pv/quilts/03miroazul.jpg","thumb":"images/2018pv/quilts/thumbs/03miroazul.jpg","w":1984,"h":1704,"index":10},{"name":"03mirocinza.jpg","title":"03mirocinza.jpg","year":"2018","season":"Primavera Verão","filename":"03mirocinza.jpg","src":"images/2018pv/quilts/03mirocinza.jpg","thumb":"images/2018pv/quilts/thumbs/03mirocinza.jpg","w":1984,"h":1704,"index":11},{"name":"03mirorosa.jpg","title":"03mirorosa.jpg","year":"2018","season":"Primavera Verão","filename":"03mirorosa.jpg","src":"images/2018pv/quilts/03mirorosa.jpg","thumb":"images/2018pv/quilts/thumbs/03mirorosa.jpg","w":1984,"h":1704,"index":12},{"name":"03mirotaupe.jpg","title":"03mirotaupe.jpg","year":"2018","season":"Primavera Verão","filename":"03mirotaupe.jpg","src":"images/2018pv/quilts/03mirotaupe.jpg","thumb":"images/2018pv/quilts/thumbs/03mirotaupe.jpg","w":1984,"h":1704,"index":13},{"name":"04dunabege.jpg","title":"04dunabege.jpg","year":"2018","season":"Primavera Verão","filename":"04dunabege.jpg","src":"images/2018pv/quilts/04dunabege.jpg","thumb":"images/2018pv/quilts/thumbs/04dunabege.jpg","w":1594,"h":1417,"index":14},{"name":"04dunabranco.jpg","title":"04dunabranco.jpg","year":"2018","season":"Primavera Verão","filename":"04dunabranco.jpg","src":"images/2018pv/quilts/04dunabranco.jpg","thumb":"images/2018pv/quilts/thumbs/04dunabranco.jpg","w":1594,"h":1417,"index":15},{"name":"04dunacinza.jpg","title":"04dunacinza.jpg","year":"2018","season":"Primavera Verão","filename":"04dunacinza.jpg","src":"images/2018pv/quilts/04dunacinza.jpg","thumb":"images/2018pv/quilts/thumbs/04dunacinza.jpg","w":1594,"h":1417,"index":16},{"name":"05formosabege.jpg","title":"05formosabege.jpg","year":"2018","season":"Primavera Verão","filename":"05formosabege.jpg","src":"images/2018pv/quilts/05formosabege.jpg","thumb":"images/2018pv/quilts/thumbs/05formosabege.jpg","w":1617,"h":1559,"index":17},{"name":"05formosabranco.jpg","title":"05formosabranco.jpg","year":"2018","season":"Primavera Verão","filename":"05formosabranco.jpg","src":"images/2018pv/quilts/05formosabranco.jpg","thumb":"images/2018pv/quilts/thumbs/05formosabranco.jpg","w":1617,"h":1559,"index":18},{"name":"05formosarosa.jpg","title":"05formosarosa.jpg","year":"2018","season":"Primavera Verão","filename":"05formosarosa.jpg","src":"images/2018pv/quilts/05formosarosa.jpg","thumb":"images/2018pv/quilts/thumbs/05formosarosa.jpg","w":1617,"h":1559,"index":19},{"name":"06troiabege.jpg","title":"06troiabege.jpg","year":"2018","season":"Primavera Verão","filename":"06troiabege.jpg","src":"images/2018pv/quilts/06troiabege.jpg","thumb":"images/2018pv/quilts/thumbs/06troiabege.jpg","w":1766,"h":1304,"index":20},{"name":"06troiabranco.jpg","title":"06troiabranco.jpg","year":"2018","season":"Primavera Verão","filename":"06troiabranco.jpg","src":"images/2018pv/quilts/06troiabranco.jpg","thumb":"images/2018pv/quilts/thumbs/06troiabranco.jpg","w":1766,"h":1304,"index":21},{"name":"06troiacinza.jpg","title":"06troiacinza.jpg","year":"2018","season":"Primavera Verão","filename":"06troiacinza.jpg","src":"images/2018pv/quilts/06troiacinza.jpg","thumb":"images/2018pv/quilts/thumbs/06troiacinza.jpg","w":1766,"h":1304,"index":22},{"name":"06troiarosa.jpg","title":"06troiarosa.jpg","year":"2018","season":"Primavera Verão","filename":"06troiarosa.jpg","src":"images/2018pv/quilts/06troiarosa.jpg","thumb":"images/2018pv/quilts/thumbs/06troiarosa.jpg","w":1766,"h":1304,"index":23},{"name":"07tamarizazul.jpg","title":"07tamarizazul.jpg","year":"2018","season":"Primavera Verão","filename":"07tamarizazul.jpg","src":"images/2018pv/quilts/07tamarizazul.jpg","thumb":"images/2018pv/quilts/thumbs/07tamarizazul.jpg","w":1766,"h":1289,"index":24},{"name":"07tamarizbege.jpg","title":"07tamarizbege.jpg","year":"2018","season":"Primavera Verão","filename":"07tamarizbege.jpg","src":"images/2018pv/quilts/07tamarizbege.jpg","thumb":"images/2018pv/quilts/thumbs/07tamarizbege.jpg","w":1766,"h":1289,"index":25},{"name":"07tamarizbranco.jpg","title":"07tamarizbranco.jpg","year":"2018","season":"Primavera Verão","filename":"07tamarizbranco.jpg","src":"images/2018pv/quilts/07tamarizbranco.jpg","thumb":"images/2018pv/quilts/thumbs/07tamarizbranco.jpg","w":1766,"h":1289,"index":26},{"name":"07tamarizcinza.jpg","title":"07tamarizcinza.jpg","year":"2018","season":"Primavera Verão","filename":"07tamarizcinza.jpg","src":"images/2018pv/quilts/07tamarizcinza.jpg","thumb":"images/2018pv/quilts/thumbs/07tamarizcinza.jpg","w":1766,"h":1289,"index":27},{"name":"07tamarizrosa.jpg","title":"07tamarizrosa.jpg","year":"2018","season":"Primavera Verão","filename":"07tamarizrosa.jpg","src":"images/2018pv/quilts/07tamarizrosa.jpg","thumb":"images/2018pv/quilts/thumbs/07tamarizrosa.jpg","w":1766,"h":1289,"index":28},{"name":"08azul.jpg","title":"08azul.jpg","year":"2018","season":"Primavera Verão","filename":"08azul.jpg","src":"images/2018pv/quilts/08azul.jpg","thumb":"images/2018pv/quilts/thumbs/08azul.jpg","w":1996,"h":1632,"index":29},{"name":"08bege.jpg","title":"08bege.jpg","year":"2018","season":"Primavera Verão","filename":"08bege.jpg","src":"images/2018pv/quilts/08bege.jpg","thumb":"images/2018pv/quilts/thumbs/08bege.jpg","w":1996,"h":1632,"index":30},{"name":"08branco.jpg","title":"08branco.jpg","year":"2018","season":"Primavera Verão","filename":"08branco.jpg","src":"images/2018pv/quilts/08branco.jpg","thumb":"images/2018pv/quilts/thumbs/08branco.jpg","w":1996,"h":1632,"index":31},{"name":"08cinza.jpg","title":"08cinza.jpg","year":"2018","season":"Primavera Verão","filename":"08cinza.jpg","src":"images/2018pv/quilts/08cinza.jpg","thumb":"images/2018pv/quilts/thumbs/08cinza.jpg","w":1996,"h":1632,"index":32},{"name":"09falésiaazul.jpg","title":"09falésiaazul.jpg","year":"2018","season":"Primavera Verão","filename":"09falésiaazul.jpg","src":"images/2018pv/quilts/09falésiaazul.jpg","thumb":"images/2018pv/quilts/thumbs/09falésiaazul.jpg","w":1655,"h":1559,"index":33},{"name":"09falésiabege.jpg","title":"09falésiabege.jpg","year":"2018","season":"Primavera Verão","filename":"09falésiabege.jpg","src":"images/2018pv/quilts/09falésiabege.jpg","thumb":"images/2018pv/quilts/thumbs/09falésiabege.jpg","w":1655,"h":1559,"index":34},{"name":"09falésiabranco.jpg","title":"09falésiabranco.jpg","year":"2018","season":"Primavera Verão","filename":"09falésiabranco.jpg","src":"images/2018pv/quilts/09falésiabranco.jpg","thumb":"images/2018pv/quilts/thumbs/09falésiabranco.jpg","w":1655,"h":1559,"index":35},{"name":"09falésiacinza.jpg","title":"09falésiacinza.jpg","year":"2018","season":"Primavera Verão","filename":"09falésiacinza.jpg","src":"images/2018pv/quilts/09falésiacinza.jpg","thumb":"images/2018pv/quilts/thumbs/09falésiacinza.jpg","w":1655,"h":1559,"index":36},{"name":"09falésiarosa.jpg","title":"09falésiarosa.jpg","year":"2018","season":"Primavera Verão","filename":"09falésiarosa.jpg","src":"images/2018pv/quilts/09falésiarosa.jpg","thumb":"images/2018pv/quilts/thumbs/09falésiarosa.jpg","w":1655,"h":1559,"index":37},{"name":"10castelobege.jpg","title":"10castelobege.jpg","year":"2018","season":"Primavera Verão","filename":"10castelobege.jpg","src":"images/2018pv/quilts/10castelobege.jpg","thumb":"images/2018pv/quilts/thumbs/10castelobege.jpg","w":1740,"h":1559,"index":38},{"name":"10castelocinza.jpg","title":"10castelocinza.jpg","year":"2018","season":"Primavera Verão","filename":"10castelocinza.jpg","src":"images/2018pv/quilts/10castelocinza.jpg","thumb":"images/2018pv/quilts/thumbs/10castelocinza.jpg","w":1740,"h":1559,"index":39},{"name":"10castelolinho.jpg","title":"10castelolinho.jpg","year":"2018","season":"Primavera Verão","filename":"10castelolinho.jpg","src":"images/2018pv/quilts/10castelolinho.jpg","thumb":"images/2018pv/quilts/thumbs/10castelolinho.jpg","w":1740,"h":1559,"index":40},{"name":"11torpesazul.jpg","title":"11torpesazul.jpg","year":"2018","season":"Primavera Verão","filename":"11torpesazul.jpg","src":"images/2018pv/quilts/11torpesazul.jpg","thumb":"images/2018pv/quilts/thumbs/11torpesazul.jpg","w":1711,"h":1559,"index":41},{"name":"11torpesbege.jpg","title":"11torpesbege.jpg","year":"2018","season":"Primavera Verão","filename":"11torpesbege.jpg","src":"images/2018pv/quilts/11torpesbege.jpg","thumb":"images/2018pv/quilts/thumbs/11torpesbege.jpg","w":1711,"h":1559,"index":42},{"name":"11torpesbege1.jpg","title":"11torpesbege1.jpg","year":"2018","season":"Primavera Verão","filename":"11torpesbege1.jpg","src":"images/2018pv/quilts/11torpesbege1.jpg","thumb":"images/2018pv/quilts/thumbs/11torpesbege1.jpg","w":1711,"h":1559,"index":43},{"name":"11torpesbranco.jpg","title":"11torpesbranco.jpg","year":"2018","season":"Primavera Verão","filename":"11torpesbranco.jpg","src":"images/2018pv/quilts/11torpesbranco.jpg","thumb":"images/2018pv/quilts/thumbs/11torpesbranco.jpg","w":1711,"h":1559,"index":44},{"name":"11torpescinza.jpg","title":"11torpescinza.jpg","year":"2018","season":"Primavera Verão","filename":"11torpescinza.jpg","src":"images/2018pv/quilts/11torpescinza.jpg","thumb":"images/2018pv/quilts/thumbs/11torpescinza.jpg","w":1711,"h":1559,"index":45},{"name":"11torpescinzaparts.jpg","title":"11torpescinzaparts.jpg","year":"2018","season":"Primavera Verão","filename":"11torpescinzaparts.jpg","src":"images/2018pv/quilts/11torpescinzaparts.jpg","thumb":"images/2018pv/quilts/thumbs/11torpescinzaparts.jpg","w":1711,"h":1559,"index":46},{"name":"11torpescommascaras.jpg","title":"11torpescommascaras.jpg","year":"2018","season":"Primavera Verão","filename":"11torpescommascaras.jpg","src":"images/2018pv/quilts/11torpescommascaras.jpg","thumb":"images/2018pv/quilts/thumbs/11torpescommascaras.jpg","w":1711,"h":1559,"index":47},{"name":"11torpesrosa.jpg","title":"11torpesrosa.jpg","year":"2018","season":"Primavera Verão","filename":"11torpesrosa.jpg","src":"images/2018pv/quilts/11torpesrosa.jpg","thumb":"images/2018pv/quilts/thumbs/11torpesrosa.jpg","w":1711,"h":1559,"index":48},{"name":"12arvoreazul.jpg","title":"12arvoreazul.jpg","year":"2018","season":"Primavera Verão","filename":"12arvoreazul.jpg","src":"images/2018pv/quilts/12arvoreazul.jpg","thumb":"images/2018pv/quilts/thumbs/12arvoreazul.jpg","w":1766,"h":1543,"index":49},{"name":"12arvorebege.jpg","title":"12arvorebege.jpg","year":"2018","season":"Primavera Verão","filename":"12arvorebege.jpg","src":"images/2018pv/quilts/12arvorebege.jpg","thumb":"images/2018pv/quilts/thumbs/12arvorebege.jpg","w":1766,"h":1543,"index":50},{"name":"12arvorecinza.jpg","title":"12arvorecinza.jpg","year":"2018","season":"Primavera Verão","filename":"12arvorecinza.jpg","src":"images/2018pv/quilts/12arvorecinza.jpg","thumb":"images/2018pv/quilts/thumbs/12arvorecinza.jpg","w":1766,"h":1543,"index":51},{"name":"12arvorerosa.jpg","title":"12arvorerosa.jpg","year":"2018","season":"Primavera Verão","filename":"12arvorerosa.jpg","src":"images/2018pv/quilts/12arvorerosa.jpg","thumb":"images/2018pv/quilts/thumbs/12arvorerosa.jpg","w":1766,"h":1543,"index":52},{"name":"13gale.jpg","title":"13gale.jpg","year":"2018","season":"Primavera Verão","filename":"13gale.jpg","src":"images/2018pv/quilts/13gale.jpg","thumb":"images/2018pv/quilts/thumbs/13gale.jpg","w":1698,"h":1559,"index":53},{"name":"13galeazul.jpg","title":"13galeazul.jpg","year":"2018","season":"Primavera Verão","filename":"13galeazul.jpg","src":"images/2018pv/quilts/13galeazul.jpg","thumb":"images/2018pv/quilts/thumbs/13galeazul.jpg","w":1698,"h":1559,"index":54},{"name":"13galebranco.jpg","title":"13galebranco.jpg","year":"2018","season":"Primavera Verão","filename":"13galebranco.jpg","src":"images/2018pv/quilts/13galebranco.jpg","thumb":"images/2018pv/quilts/thumbs/13galebranco.jpg","w":1698,"h":1559,"index":55},{"name":"13galecinza.jpg","title":"13galecinza.jpg","year":"2018","season":"Primavera Verão","filename":"13galecinza.jpg","src":"images/2018pv/quilts/13galecinza.jpg","thumb":"images/2018pv/quilts/thumbs/13galecinza.jpg","w":1698,"h":1559,"index":56},{"name":"13galecinzaparts.jpg","title":"13galecinzaparts.jpg","year":"2018","season":"Primavera Verão","filename":"13galecinzaparts.jpg","src":"images/2018pv/quilts/13galecinzaparts.jpg","thumb":"images/2018pv/quilts/thumbs/13galecinzaparts.jpg","w":1698,"h":1559,"index":57},{"name":"13galerosa.jpg","title":"13galerosa.jpg","year":"2018","season":"Primavera Verão","filename":"13galerosa.jpg","src":"images/2018pv/quilts/13galerosa.jpg","thumb":"images/2018pv/quilts/thumbs/13galerosa.jpg","w":1698,"h":1559,"index":58},{"name":"14azul.jpg","title":"14azul.jpg","year":"2018","season":"Primavera Verão","filename":"14azul.jpg","src":"images/2018pv/quilts/14azul.jpg","thumb":"images/2018pv/quilts/thumbs/14azul.jpg","w":1766,"h":1543,"index":59},{"name":"14bege.jpg","title":"14bege.jpg","year":"2018","season":"Primavera Verão","filename":"14bege.jpg","src":"images/2018pv/quilts/14bege.jpg","thumb":"images/2018pv/quilts/thumbs/14bege.jpg","w":1766,"h":1543,"index":60},{"name":"14branco.jpg","title":"14branco.jpg","year":"2018","season":"Primavera Verão","filename":"14branco.jpg","src":"images/2018pv/quilts/14branco.jpg","thumb":"images/2018pv/quilts/thumbs/14branco.jpg","w":1766,"h":1543,"index":61},{"name":"14cinza.jpg","title":"14cinza.jpg","year":"2018","season":"Primavera Verão","filename":"14cinza.jpg","src":"images/2018pv/quilts/14cinza.jpg","thumb":"images/2018pv/quilts/thumbs/14cinza.jpg","w":1766,"h":1543,"index":62},{"name":"14rrosa.jpg","title":"14rrosa.jpg","year":"2018","season":"Primavera Verão","filename":"14rrosa.jpg","src":"images/2018pv/quilts/14rrosa.jpg","thumb":"images/2018pv/quilts/thumbs/14rrosa.jpg","w":1766,"h":1543,"index":63},{"name":"15salema.jpg","title":"15salema.jpg","year":"2018","season":"Primavera Verão","filename":"15salema.jpg","src":"images/2018pv/quilts/15salema.jpg","thumb":"images/2018pv/quilts/thumbs/15salema.jpg","w":1766,"h":1179,"index":64},{"name":"16concha.jpg","title":"16concha.jpg","year":"2018","season":"Primavera Verão","filename":"16concha.jpg","src":"images/2018pv/quilts/16concha.jpg","thumb":"images/2018pv/quilts/thumbs/16concha.jpg","w":1766,"h":1247,"index":65},{"name":"17farol.jpg","title":"17farol.jpg","year":"2018","season":"Primavera Verão","filename":"17farol.jpg","src":"images/2018pv/quilts/17farol.jpg","thumb":"images/2018pv/quilts/thumbs/17farol.jpg","w":1766,"h":1179,"index":66},{"name":"18nice.jpg","title":"18nice.jpg","year":"2018","season":"Primavera Verão","filename":"18nice.jpg","src":"images/2018pv/quilts/18nice.jpg","thumb":"images/2018pv/quilts/thumbs/18nice.jpg","w":1766,"h":1179,"index":67},{"name":"19estela.jpg","title":"19estela.jpg","year":"2018","season":"Primavera Verão","filename":"19estela.jpg","src":"images/2018pv/quilts/19estela.jpg","thumb":"images/2018pv/quilts/thumbs/19estela.jpg","w":1766,"h":1179,"index":68},{"name":"9.jpg","title":"9.jpg","year":"2018","season":"Primavera Verão","filename":"9.jpg","src":"images/2018pv/quilts/9.jpg","thumb":"images/2018pv/quilts/thumbs/9.jpg","w":1766,"h":1543,"index":69},{"name":"ofirantracite.jpg","title":"ofirantracite.jpg","year":"2018","season":"Primavera Verão","filename":"ofirantracite.jpg","src":"images/2018pv/quilts/ofirantracite.jpg","thumb":"images/2018pv/quilts/thumbs/ofirantracite.jpg","w":1674,"h":1417,"index":70},{"name":"ofircanela.jpg","title":"ofircanela.jpg","year":"2018","season":"Primavera Verão","filename":"ofircanela.jpg","src":"images/2018pv/quilts/ofircanela.jpg","thumb":"images/2018pv/quilts/thumbs/ofircanela.jpg","w":1674,"h":1417,"index":71},{"name":"ofircinza.jpg","title":"ofircinza.jpg","year":"2018","season":"Primavera Verão","filename":"ofircinza.jpg","src":"images/2018pv/quilts/ofircinza.jpg","thumb":"images/2018pv/quilts/thumbs/ofircinza.jpg","w":1674,"h":1417,"index":72},{"name":"ofirverde.jpg","title":"ofirverde.jpg","year":"2018","season":"Primavera Verão","filename":"ofirverde.jpg","src":"images/2018pv/quilts/ofirverde.jpg","thumb":"images/2018pv/quilts/thumbs/ofirverde.jpg","w":1674,"h":1417,"index":73}]